deribit_wrapper/__init__.py
deribit_wrapper/account_management.py
deribit_wrapper/authentication.py
deribit_wrapper/base.py
deribit_wrapper/core.py
deribit_wrapper/exceptions.py
deribit_wrapper/market_data.py
deribit_wrapper/trading.py
deribit_wrapper/utilities.py
dev_scripts/__init__.py
dev_scripts/config_dev.py
dev_scripts/debug_account_management.py
dev_scripts/debug_authentication.py
dev_scripts/debug_market_data.py
dev_scripts/utilities_dev.py
tests/__init__.py
tests/conftest.py
tests/test_authentication.py
tests/test_base.py
deribit_wrapper-0.4.2.dist-info/LICENSE
deribit_wrapper-0.4.2.dist-info/METADATA
deribit_wrapper-0.4.2.dist-info/WHEEL
deribit_wrapper-0.4.2.dist-info/top_level.txt
deribit_wrapper-0.4.2.dist-info/RECORD
