Metadata-Version: 2.1
Name: deribit-wrapper
Version: 0.4.2
Summary: A Python wrapper for seamless integration with Deribit's trading API, offering easy access to market data, account management, and trading operations.
Home-page: https://github.com/AntonioVentilii/deribit-wrapper
Author: Antonio Ventilii
Author-email: antonioventilii@gmail.com
License: MIT
Project-URL: Source Code, https://github.com/AntonioVentilii/deribit-wrapper
Project-URL: Issue Tracker, https://github.com/AntonioVentilii/deribit-wrapper/issues
Keywords: deribit api wrapper cryptocurrency trading
Classifier: Programming Language :: Python :: 3
Classifier: License :: OSI Approved :: MIT License
Classifier: Operating System :: OS Independent
Requires-Python: >=3.10
License-File: LICENSE
Requires-Dist: requests
Requires-Dist: numpy
Requires-Dist: pandas
Requires-Dist: urllib3
Requires-Dist: progressbar2
